randomvariates/__init__.py
randomvariates/random.py
randvars-0.0.17.dist-info/METADATA
randvars-0.0.17.dist-info/WHEEL
randvars-0.0.17.dist-info/top_level.txt
randvars-0.0.17.dist-info/RECORD
