Metadata-Version: 2.1
Name: randvars
Version: 0.0.17
Summary: A library of random variate generation routines
Home-page: https://github.com/jgoodie/randomvariates
Author: John Goodman
Author-email: john.goodman@gmail.com
License: MIT
Download-URL: https://pypi.org/project/randvars/
Keywords: Random,Random Generator,Random Variates,Random Variables
Platform: UNKNOWN
Requires-Dist: numpy
